zweifach/__init__.py
zweifach/apps.py
zweifach/checks.py
zweifach/forms.py
zweifach/middleware.py
zweifach/models.py
zweifach/tests.py
zweifach/urls.py
zweifach/views.py
zweifach/migrations/__init__.py
zweifach/templates/zweifach/base.html
zweifach/templates/zweifach/setup.html
zweifach/templates/zweifach/verify.html
zweifach-1.0.3.dist-info/METADATA
zweifach-1.0.3.dist-info/WHEEL
zweifach-1.0.3.dist-info/top_level.txt
zweifach-1.0.3.dist-info/RECORD
